Workbook

Sheet Summary
A1: Zefanya Mobile App - Combined Test Results
A2: Static code review of lib.zip (mock-data build). Not run on a device. Blocked = needs phone, live API or seeded data. Edit Status on the All Results sheet and these counts update.
A4: Workbook | B4: Total | C4: Pass | D4: Fail | E4: Blocked | F4: Not Run | G4: Pass rate
A5: Buyer - Account Creation | B5: =COUNTIF('All Results'!$A$2:$A$378,A5) -> 42 | C5: =COUNTIFS('All Results'!$A$2:$A$378,$A5,'All Results'!$H$2:$H$378,"Pass") -> 18 | D5: =COUNTIFS('All Results'!$A$2:$A$378,$A5,'All Results'!$H$2:$H$378,"Fail") -> 9 | E5: =COUNTIFS('All Results'!$A$2:$A$378,$A5,'All Results'!$H$2:$H$378,"Blocked") -> 15 | F5: =B5-C5-D5-E5 -> 0 | G5: =IF(B5=0,0,C5/B5) -> 0.42857143
A6: Courier - Account Creation | B6: =COUNTIF('All Results'!$A$2:$A$378,A6) -> 52 | C6: =COUNTIFS('All Results'!$A$2:$A$378,$A6,'All Results'!$H$2:$H$378,"Pass") -> 2 | D6: =COUNTIFS('All Results'!$A$2:$A$378,$A6,'All Results'!$H$2:$H$378,"Fail") -> 9 | E6: =COUNTIFS('All Results'!$A$2:$A$378,$A6,'All Results'!$H$2:$H$378,"Blocked") -> 41 | F6: =B6-C6-D6-E6 -> 0 | G6: =IF(B6=0,0,C6/B6) -> 0.038461538
A7: Rider - Account Creation | B7: =COUNTIF('All Results'!$A$2:$A$378,A7) -> 47 | C7: =COUNTIFS('All Results'!$A$2:$A$378,$A7,'All Results'!$H$2:$H$378,"Pass") -> 1 | D7: =COUNTIFS('All Results'!$A$2:$A$378,$A7,'All Results'!$H$2:$H$378,"Fail") -> 8 | E7: =COUNTIFS('All Results'!$A$2:$A$378,$A7,'All Results'!$H$2:$H$378,"Blocked") -> 38 | F7: =B7-C7-D7-E7 -> 0 | G7: =IF(B7=0,0,C7/B7) -> 0.021276596
A8: Buyer - Modules | B8: =COUNTIF('All Results'!$A$2:$A$378,A8) -> 131 | C8: =COUNTIFS('All Results'!$A$2:$A$378,$A8,'All Results'!$H$2:$H$378,"Pass") -> 21 | D8: =COUNTIFS('All Results'!$A$2:$A$378,$A8,'All Results'!$H$2:$H$378,"Fail") -> 85 | E8: =COUNTIFS('All Results'!$A$2:$A$378,$A8,'All Results'!$H$2:$H$378,"Blocked") -> 25 | F8: =B8-C8-D8-E8 -> 0 | G8: =IF(B8=0,0,C8/B8) -> 0.16030534
A9: Courier - Modules | B9: =COUNTIF('All Results'!$A$2:$A$378,A9) -> 52 | C9: =COUNTIFS('All Results'!$A$2:$A$378,$A9,'All Results'!$H$2:$H$378,"Pass") -> 0 | D9: =COUNTIFS('All Results'!$A$2:$A$378,$A9,'All Results'!$H$2:$H$378,"Fail") -> 46 | E9: =COUNTIFS('All Results'!$A$2:$A$378,$A9,'All Results'!$H$2:$H$378,"Blocked") -> 6 | F9: =B9-C9-D9-E9 -> 0 | G9: =IF(B9=0,0,C9/B9) -> 0
A10: Rider - Modules | B10: =COUNTIF('All Results'!$A$2:$A$378,A10) -> 53 | C10: =COUNTIFS('All Results'!$A$2:$A$378,$A10,'All Results'!$H$2:$H$378,"Pass") -> 2 | D10: =COUNTIFS('All Results'!$A$2:$A$378,$A10,'All Results'!$H$2:$H$378,"Fail") -> 39 | E10: =COUNTIFS('All Results'!$A$2:$A$378,$A10,'All Results'!$H$2:$H$378,"Blocked") -> 12 | F10: =B10-C10-D10-E10 -> 0 | G10: =IF(B10=0,0,C10/B10) -> 0.037735849
A11: Total | B11: =SUM(B5:B10) -> 377 | C11: =SUM(C5:C10) -> 44 | D11: =SUM(D5:D10) -> 196 | E11: =SUM(E5:E10) -> 137 | F11: =SUM(F5:F10) -> 0 | G11: =IF(B11=0,0,C11/B11) -> 0.11671088

Sheet All Results
A1: Workbook | B1: Sheet | C1: Module | D1: Test Case ID | E1: Test Scenario | F1: Expected Result | G1: Actual Result | H1: Status | I1: Remarks
A2: Buyer - Account Creation | B2: Buyer | C2: Registration Form | D2: TC-BUY-001 | E2: Register with all valid data | F2: The form is accepted with no validation errors. A success message is shown, a 6-digit OTP is sent to the email, and the email verification screen opens. The account is saved with status Unverified. | G2: Mock build: Submit goes straight to the Under Review screen and no OTP is sent. The form also asks for Sex, Middle Initial, address and a Gov ID upload that are not in the test data. | H2: Blocked | I2: Needs live Laravel API (--dart-define=zefanya.useLiveApi=true). Check OTP email and Unverified status there.
A3: Buyer - Account Creation | B3: Buyer | C3: Required Fields | D3: TC-BUY-002 | E3: Submit a completely empty form | F3: Registration is blocked. A required-field message is shown for every mandatory field. No account is created and no OTP is sent. | G3: Continue on step 1 flags every empty required field (names, sex, email, phone, date of birth). Nothing is submitted. | H3: Pass | I3: Wizard validates per step; password, address and ID are flagged when their step is reached.
A4: Buyer - Account Creation | B4: Buyer | C4: Required Fields | D4: TC-BUY-003 | E4: Leave one required field blank at a time | F4: Each time, registration is blocked and a required-field message is shown on the blank field only. Other entered values (except passwords and uploads) are kept. No account is created. | G4: Each required field shows its own message; other values stay in the form. | H4: Pass
A5: Buyer - Account Creation | B5: Buyer | C5: Name | D5: TC-BUY-004 | E5: Name with numbers or symbols | F5: Registration is blocked. A message on each name field says only letters are allowed. | G5: Names with numbers and symbols are accepted. Only length of at least 2 is checked. | H5: Fail | I5: Add a letters/space/hyphen/apostrophe/period rule (A2).
A6: Buyer - Account Creation | B6: Buyer | C6: Name | D6: TC-BUY-005 | E6: Name with ñ and allowed punctuation | F6: The names are accepted and saved exactly as typed, including ñ. | G6: Names with ñ, hyphen and apostrophe are accepted and kept as typed. | H6: Pass
A7: Buyer - Account Creation | B7: Buyer | C7: Name | D7: TC-BUY-006 | E7: Name length at the limits | F7: 1 and 51 characters are rejected with a length message. 2 and 50 characters are accepted. | G7: 1 character shows "First name is required" (not a length message). 51 characters is accepted; there is no 50-character limit. | H7: Fail | I7: Add max length 50 and a length message.
A8: Buyer - Account Creation | B8: Buyer | C8: Date of Birth | D8: TC-BUY-007 | E8: Age at the 18-year limit | F8: The 17-year-old date is rejected with a message that the person must be at least 18. The other two dates are accepted. | G8: The age is calculated but never checked. A 17-year-old date of birth is accepted. | H8: Fail | I8: registration_screen.dart _pickDob: add age >= 18 validation (A6).
A9: Buyer - Account Creation | B9: Buyer | C9: Date of Birth | D9: TC-BUY-008 | E9: Date of birth in the future | F9: Registration is blocked. A message asks for a valid date of birth. If a date picker is used, future dates cannot be selected. | G9: The date picker stops at today, so a future date cannot be chosen. | H9: Pass
A10: Buyer - Account Creation | B10: Buyer | C10: Email | D10: TC-BUY-009 | E10: Email in an invalid format | F10: Each value is rejected with a message asking for a valid email address. No account is created. | G10: All five values are rejected with "Enter a valid email address". | H10: Pass
A11: Buyer - Account Creation | B11: Buyer | C11: Email | D11: TC-BUY-010 | E11: Email that is already registered | F11: Registration is blocked. A message says the email is already in use. No account is created. | G11: Mock repository has no account store, so a duplicate email is never detected. | H11: Blocked | I11: Needs live Laravel API (--dart-define=zefanya.useLiveApi=true).
A12: Buyer - Account Creation | B12: Buyer | C12: Email | D12: TC-BUY-011 | E12: Registered email typed in capital letters | F12: The email is treated as a duplicate. Registration is blocked. | G12: Duplicate detection (case-insensitive) is a server rule; the mock does not do it. | H12: Blocked | I12: Needs live Laravel API (--dart-define=zefanya.useLiveApi=true).
A13: Buyer - Account Creation | B13: Buyer | C13: Email | D13: TC-BUY-012 | E13: Email with spaces before and after | F13: The spaces are removed and the email is saved as buyer.test01@example.com. | G13: Spaces are trimmed before validating and before submitting. | H13: Pass
A14: Buyer - Account Creation | B14: Buyer | C14: Mobile Number | D14: TC-BUY-013 | E14: Mobile number in an invalid format | F14: Each value is rejected with a message asking for a valid mobile number. | G14: All four values are rejected with "Enter a valid PH number (09XXXXXXXXX)". | H14: Pass
A15: Buyer - Account Creation | B15: Buyer | C15: Mobile Number | D15: TC-BUY-014 | E15: Mobile number length at the limits | F15: 10 and 12 digits are rejected with a length message. 11 digits is accepted. | G15: 10 and 12 digits are rejected; 11 digits is accepted. | H15: Pass | I15: The message is a format message, not a length message.
A16: Buyer - Account Creation | B16: Buyer | C16: Mobile Number | D16: TC-BUY-015 | E16: Mobile number that is already registered | F16: Registration is blocked. A message says the mobile number is already in use. | G16: Duplicate mobile numbers are only detectable by the server. | H16: Blocked | I16: Needs live Laravel API (--dart-define=zefanya.useLiveApi=true).
A17: Buyer - Account Creation | B17: Buyer | C17: Mobile Number | D17: TC-BUY-016 | E17: Registered number entered in +63 format | F17: The +63 format is recognised as the same number. Registration is blocked. A message says the mobile number is already in use. | G17: +63 and 09 forms both pass the format check; treating them as the same number is a server rule. | H17: Blocked | I17: Needs live Laravel API (--dart-define=zefanya.useLiveApi=true).
A18: Buyer - Account Creation | B18: Buyer | C18: Password | D18: TC-BUY-017 | E18: Password length at the limit | F18: 7 characters is rejected with a minimum-length message. 8 characters is accepted. | G18: 7 characters is rejected with "Use at least 8 characters"; 8 is accepted. | H18: Pass
A19: Buyer - Account Creation | B19: Buyer | C19: Password | D19: TC-BUY-018 | E19: Password missing a required character type | F19: Each password is rejected with a message stating the password rule. No account is created. | G19: All four passwords are accepted. Only the 8-character minimum is enforced; no upper/lower/number/special rule. | H19: Fail | I19: Add the A5 rule, or change A5 to match the server.
A20: Buyer - Account Creation | B20: Buyer | C20: Password | D20: TC-BUY-019 | E20: Confirm Password does not match | F20: Registration is blocked. A message says the passwords do not match. | G20: Shows "Passwords don't match". | H20: Pass
A21: Buyer - Account Creation | B21: Buyer | C21: Password | D21: TC-BUY-020 | E21: Password is hidden while typing | F21: Characters are hidden as dots by default. The icon reveals the password, then hides it again. | G21: Password and confirmation are obscured; the eye icon toggles each one. | H21: Pass
A22: Buyer - Account Creation | B22: Buyer | C22: Terms and Privacy Policy | D22: TC-BUY-021 | E22: Register without accepting the terms | F22: Registration is blocked. A message says the Terms and Privacy Policy must be accepted. | G22: No Terms and Privacy checkbox on the registration form. The only terms checkbox is at checkout. | H22: Fail
A23: Buyer - Account Creation | B23: Buyer | C23: Registration Form | D23: TC-BUY-022 | E23: Tap Register several times quickly | F23: Only one account is created and only one OTP email is sent. No duplicate-email error screen appears. | G23: The submit button is disabled while the request runs, so repeated taps do nothing. | H23: Pass | I23: The "only one OTP email" part needs the live API.
A24: Buyer - Account Creation | B24: Buyer | C24: Email Verification (OTP) | D24: TC-BUY-023 | E24: Verify with the correct OTP | F24: Verification succeeds. The account status changes from Unverified to Active. A success message is shown and the login screen (or home screen) opens. | G24: After the correct code (123456 in mock) the status becomes Pending Approval and the Under Review screen opens. It never becomes Active. | H24: Fail | I24: Rule conflict: A12 says buyers become Active after OTP, but the app treats them as needing admin approval. Align one of them.
A25: Buyer - Account Creation | B25: Buyer | C25: Email Verification (OTP) | D25: TC-BUY-024 | E25: Verify with an incorrect OTP | F25: Verification fails with an invalid-code message. The account stays Unverified. | G25: A wrong code is rejected with "That code doesn't match. Please try again." and the account stays unverified. | H25: Pass | I25: Mock accepts only 123456; live wording comes from the server.
A26: Buyer - Account Creation | B26: Buyer | C26: Email Verification (OTP) | D26: TC-BUY-025 | E26: OTP in the wrong format | F26: Each value is rejected. The account stays Unverified. | G26: Letters cannot be typed (digits only). 5 digits shows "The code is six digits." Blank shows a prompt. A 7th digit cannot be typed. | H26: Pass
A27: Buyer - Account Creation | B27: Buyer | C27: Email Verification (OTP) | D27: TC-BUY-026 | E27: Verify with an expired OTP | F27: Verification fails with a message that the code has expired, and a Resend option is offered. The account stays Unverified. | G27: Expiry is decided by the server. The OTP screen has no expired state or countdown. | H27: Blocked | I27: Needs live Laravel API (--dart-define=zefanya.useLiveApi=true).
A28: Buyer - Account Creation | B28: Buyer | C28: Email Verification (OTP) | D28: TC-BUY-027 | E28: Resend OTP | F28: A new OTP email arrives. The first code is rejected. The second code is accepted and the account is verified. | G28: Resend has a 30-second cooldown and shows "A new code has been sent." The mock resend sends nothing and the old code stays valid. | H28: Blocked | I28: Needs live Laravel API (--dart-define=zefanya.useLiveApi=true).
A29: Buyer - Account Creation | B29: Buyer | C29: Email Verification (OTP) | D29: TC-BUY-028 | E29: Log in before verifying the email | F29: The user is not given access. The verification screen or a message asking to verify the email is shown. | G29: Mock login accepts any email and password and opens the buyer home, even for an unverified account. | H29: Fail | I29: Live mode depends on the server answer; retest with the live API.
A30: Buyer - Account Creation | B30: Buyer | C30: Access Control | D30: TC-BUY-029 | E30: Log in with the new verified account | F30: Login succeeds. The buyer home screen opens and the name Juan Miguel is shown. | G30: Mock login accepts any credentials, so this cannot prove a real verified account works. | H30: Blocked | I30: Needs live Laravel API (--dart-define=zefanya.useLiveApi=true).
A31: Buyer - Account Creation | B31: Buyer | C31: Access Control | D31: TC-BUY-030 | E31: Open another role's screens | F31: No other role's menus are shown. Each deep link shows an access-denied message or returns to the buyer home screen. The API request is refused (401/403). No data from the other role is shown. | G31: The app has no deep links; the shell is chosen from the saved role. 401/403 handling is server-side. | H31: Blocked | I31: Needs live Laravel API (--dart-define=zefanya.useLiveApi=true). Also needs a proxy tool (M11).
A32: Buyer - Account Creation | B32: Buyer | C32: Registration Form | D32: TC-BUY-031 | E32: [Mobile] Each field opens the right keyboard | F32: Each field opens the keyboard listed in the test data. Password fields show no autocorrect or word suggestions. No field opens a keyboard that cannot type its valid value. | G32: Email uses the email keyboard, phone uses the phone keypad, names use the name keyboard, password fields are obscured. | H32: Pass | I32: Code review only; confirm on a phone.
A33: Buyer - Account Creation | B33: Buyer | C33: Registration Form | D33: TC-BUY-032 | E33: [Mobile] Keyboard never hides the active field or Register | F33: The focused field always scrolls into view above the keyboard, with its error message visible. Register can be reached and tapped. The keyboard closes when Done or the background is tapped. | G33: Cannot be judged from code. | H33: Blocked | I33: Needs a phone or emulator; code review only.
A34: Buyer - Account Creation | B34: Buyer | C34: Registration Form | D34: TC-BUY-033 | E34: [Mobile] App sent to the background while filling the form | F34: Each time, the app returns to the same form with every typed value still there (passwords may be cleared). The app does not restart, crash or jump to the login screen. No account is created until Register is tapped. | G34: Cannot be judged from code. Controllers live in the wizard state, so values should survive a pause. | H34: Blocked | I34: Needs a phone or emulator; code review only.
A35: Buyer - Account Creation | B35: Buyer | C35: Registration Form | D35: TC-BUY-034 | E35: [Mobile] Rotate the phone while the form has data | F35: Either the app stays in portrait, or the layout switches to landscape and back keeping every value and the error message. Nothing is cleared and the app does not crash. | G35: No orientation lock in code, so landscape is possible. Needs a device check. | H35: Blocked | I35: Needs a phone or emulator; code review only.
A36: Buyer - Account Creation | B36: Buyer | C36: Registration Form | D36: TC-BUY-035 | E36: [Mobile] Register with no internet connection | F36: Step 3: a clear no-internet message is shown, the typed data stays on the form, the app does not crash, and no account is created. Step 4: the account is saved once: exactly one account and one OTP email. | G36: Mock mode never touches the network. The live path shows the NetworkException message in a snackbar and keeps the form. | H36: Blocked | I36: Needs live Laravel API (--dart-define=zefanya.useLiveApi=true). Use Airplane mode.
A37: Buyer - Account Creation | B37: Buyer | C37: Registration Form | D37: TC-BUY-036 | E37: [Mobile] Connection drops right after tapping Register | F37: The app shows a connection error or a waiting state, never a frozen screen. In the end exactly one account exists with this email. If the first attempt was saved, the app continues normally (or says the account already exists and lets the user continue); the account is never left in a state the user cannot reach. | G37: Needs a real request to drop. | H37: Blocked | I37: Needs live Laravel API (--dart-define=zefanya.useLiveApi=true).
A38: Buyer - Account Creation | B38: Buyer | C38: Email Verification (OTP) | D38: TC-BUY-037 | E38: [Mobile] Paste the OTP copied from the mail app | F38: All 6 digits fill the OTP field (every box, in order, when it is split into boxes). Verification succeeds and the status changes exactly as in the correct-OTP case. | G38: The OTP field is digits-only and limited to 6, so a pasted 6-digit code fills it. | H38: Pass | I38: It is one field, not split boxes. No one-time-code autofill hint is set.
A39: Buyer - Account Creation | B39: Buyer | C39: Email Verification (OTP) | D39: TC-BUY-038 | E39: [Mobile] OTP countdown after switching to the mail app | F39: After step 2 the verification screen is still open and shows about 3 minutes left (the countdown kept running; it did not restart at 5:00). In step 3 the code is rejected as expired and Resend is offered. | G39: There is no countdown on the OTP screen, so nothing shows time left. | H39: Fail
A40: Buyer - Account Creation | B40: Buyer | C40: Email Verification (OTP) | D40: TC-BUY-039 | E40: [Mobile] System Back on the form and the verification screen | F40: Leaving a form with typed data asks first, and Cancel keeps every value. Back from the verification screen does not create a second account; the account stays Unverified, and the next login brings the user back to verification. | G40: Back on the first registration step leaves without asking. DirtyGuard is only used on Edit Profile. | H40: Fail | I40: Wrap the registration wizard in DirtyGuard (M8).
A41: Buyer - Account Creation | B41: Buyer | C41: Registration Form | D41: TC-BUY-040 | E41: [Mobile] Large system font on a small screen | F41: All labels, placeholders, error messages and buttons can be read in full; none are cut off or overlapping. The screen scrolls to every field and Register can be tapped. | G41: main.dart clamps text scale to 0.85-1.3x, so the largest system font is capped. Overflow cannot be judged from code. | H41: Blocked | I41: Needs a phone or emulator; code review only.
A42: Buyer - Account Creation | B42: Buyer | C42: Access Control | D42: TC-BUY-041 | E42: [Mobile] Stay logged in after closing the app or restarting the phone | F42: Each time the app opens on the buyer home screen still logged in, showing Juan Miguel. It does not ask to log in again and shows no other user's data. | G42: Status and role are saved and restored at startup, so the app opens logged in. | H42: Pass | I42: Live mode also keeps the token in secure storage.
A43: Buyer - Account Creation | B43: Buyer | C43: Access Control | D43: TC-BUY-042 | E43: [Mobile] Back after logging out | F43: The login screen stays. No screen with account data appears again, and the app does not log back in by itself. | G43: Logout clears the session and returns to the root; the login screen shows and nothing logs back in. | H43: Pass
A44: Courier - Account Creation | B44: Courier | C44: Add Courier Form | D44: TC-COU-001 | E44: Create a courier with all valid data | F44: The courier is saved with no validation errors and appears in the courier list of Bilis Hatid Express Inc. with status Pending Activation, home hub HUB-QC, 4-Wheeler Closed Van Truck and 3,000 kg. An activation email is sent to ernesto.villareal@example.com. | G44: The Add Courier form is not in the Flutter app. | H44: Blocked | I44: Out of scope for the mobile app: Add Courier is a Logistics (web) form. The app has a public courier sign-up instead.
A45: Courier - Account Creation | B45: Courier | C45: Required Fields | D45: TC-COU-002 | E45: Submit a completely empty form | F45: Saving is blocked. A required-field message is shown for every mandatory field. No courier is created and no email is sent. | G45: The Add Courier form is not in the Flutter app. | H45: Blocked | I45: Out of scope for the mobile app: Add Courier is a Logistics (web) form. The app has a public courier sign-up instead.
A46: Courier - Account Creation | B46: Courier | C46: Required Fields | D46: TC-COU-003 | E46: Leave one required field blank at a time | F46: Each time, saving is blocked and a required-field message is shown on the blank field only. Other entered values (except uploads) are kept. No courier is created. | G46: The Add Courier form is not in the Flutter app. | H46: Blocked | I46: Out of scope for the mobile app: Add Courier is a Logistics (web) form. The app has a public courier sign-up instead.
A47: Courier - Account Creation | B47: Courier | C47: Name | D47: TC-COU-004 | E47: Name with numbers or symbols | F47: Saving is blocked. A message on each name field says only letters are allowed. | G47: The Add Courier form is not in the Flutter app. | H47: Blocked | I47: Out of scope for the mobile app: Add Courier is a Logistics (web) form. The app has a public courier sign-up instead.
A48: Courier - Account Creation | B48: Courier | C48: Name | D48: TC-COU-005 | E48: Name length at the limits | F48: 1 and 51 characters are rejected with a length message. 2 and 50 characters are accepted. | G48: The Add Courier form is not in the Flutter app. | H48: Blocked | I48: Out of scope for the mobile app: Add Courier is a Logistics (web) form. The app has a public courier sign-up instead.
A49: Courier - Account Creation | B49: Courier | C49: Date of Birth | D49: TC-COU-006 | E49: Age at the 18-year limit | F49: The 17-year-old date is rejected with a message that the person must be at least 18. The other two dates are accepted. A future date cannot be picked. | G49: The Add Courier form is not in the Flutter app. | H49: Blocked | I49: Out of scope for the mobile app: Add Courier is a Logistics (web) form. The app has a public courier sign-up instead.
A50: Courier - Account Creation | B50: Courier | C50: Email | D50: TC-COU-007 | E50: Email in an invalid format | F50: Each value is rejected with a message asking for a valid email address. No courier is created. | G50: The Add Courier form is not in the Flutter app. | H50: Blocked | I50: Out of scope for the mobile app: Add Courier is a Logistics (web) form. The app has a public courier sign-up instead.
A51: Courier - Account Creation | B51: Courier | C51: Email | D51: TC-COU-008 | E51: Email already used by a rider or a buyer | F51: Both are blocked with a message that the email is already in use. The same person cannot be both a rider and a courier with one email. No courier is created. | G51: The Add Courier form is not in the Flutter app. | H51: Blocked | I51: Out of scope for the mobile app: Add Courier is a Logistics (web) form. The app has a public courier sign-up instead.
A52: Courier - Account Creation | B52: Courier | C52: Mobile Number | D52: TC-COU-009 | E52: Mobile number in an invalid format | F52: Each value is rejected with a message asking for a valid mobile number. | G52: The Add Courier form is not in the Flutter app. | H52: Blocked | I52: Out of scope for the mobile app: Add Courier is a Logistics (web) form. The app has a public courier sign-up instead.
A53: Courier - Account Creation | B53: Courier | C53: Mobile Number | D53: TC-COU-010 | E53: Mobile number length at the limits | F53: 10 and 12 digits are rejected with a length message. 11 digits is accepted. | G53: The Add Courier form is not in the Flutter app. | H53: Blocked | I53: Out of scope for the mobile app: Add Courier is a Logistics (web) form. The app has a public courier sign-up instead.
A54: Courier - Account Creation | B54: Courier | C54: Mobile Number | D54: TC-COU-011 | E54: Mobile number already used by a rider | F54: Both are blocked with a message that the mobile number is already in use (the +63 form is the same number). | G54: The Add Courier form is not in the Flutter app. | H54: Blocked | I54: Out of scope for the mobile app: Add Courier is a Logistics (web) form. The app has a public courier sign-up instead.
A55: Courier - Account Creation | B55: Courier | C55: License and Vehicle | D55: TC-COU-012 | E55: Driver's license number in an invalid format | F55: Each value is rejected with a message showing the format A00-00-000000. | G55: The Add Courier form is not in the Flutter app. | H55: Blocked | I55: Out of scope for the mobile app: Add Courier is a Logistics (web) form. The app has a public courier sign-up instead.
... A91: Courier - Account Creation | B91: Courier | C91: Add Courier Form | D91: TC-COU-048 | E91: [Mobile] Large system font on a small screen | F91: All labels, placeholders, error messages and buttons can be read in full; none are cut off or overlapping. The screen scrolls to every field and Save can be tapped. | G91: Tests the Add Courier form, which is not in the app. | H91: Blocked | I91: Out of scope for the mobile app: Add Courier is a Logistics (web) form. The app has a public courier sign-up instead.
A92: Courier - Account Creation | B92: Courier | C92: Account Activation | D92: TC-COU-049 | E92: [Mobile] Activation link opened on the courier's phone with the app installed | F92: The link opens the app's Set Password screen (or a mobile web page that leads back to the app). Activation succeeds, the status becomes Active, and the courier logs in to the courier home screen showing Rogelio Dimaculangan. | G92: The app has no deep-link or app-link handling, so the activation link cannot open Set Password. | H92: Fail
A93: Courier - Account Creation | B93: Courier | C93: Account Activation | D93: TC-COU-050 | E93: [Mobile] Activation link opened on a phone without the app | F93: The link opens a mobile web page to set the password, or the app's store page with clear instructions. No blank or error page. | G93: No activation web page or store fallback exists in the app. | H93: Fail | I93: Needs the web side.
A94: Courier - Account Creation | B94: Courier | C94: Access Control | D94: TC-COU-051 | E94: [Mobile] Stay logged in after closing the app or restarting the phone | F94: Each time the app opens on the courier home screen still logged in, showing Ernesto Villareal. It does not ask to log in again and shows no other user's data. | G94: Courier session is saved and restored at startup (same code path as buyer). | H94: Pass | I94: Courier home does not show company/hub/truck.
A95: Courier - Account Creation | B95: Courier | C95: Access Control | D95: TC-COU-052 | E95: [Mobile] Back after logging out | F95: The login screen stays. No screen with account data appears again, and the app does not log back in by itself. | G95: Logout clears the session and returns to the root login screen. | H95: Pass
A96: Rider - Account Creation | B96: Rider | C96: Add Rider Form | D96: TC-RID-001 | E96: Create a rider with all valid data | F96: The rider is saved with no validation errors and appears in the rider list of Bilis Hatid Express Inc. with status Pending Activation. An activation email is sent to pedrojose.garcia@example.com. | G96: The Add Rider form is not in the Flutter app. | H96: Blocked | I96: Out of scope for the mobile app: the app has no Rider role or Add Rider form (Logistics function, web).
A97: Rider - Account Creation | B97: Rider | C97: Required Fields | D97: TC-RID-002 | E97: Submit a completely empty form | F97: Saving is blocked. A required-field message is shown for every mandatory field. No rider is created and no email is sent. | G97: The Add Rider form is not in the Flutter app. | H97: Blocked | I97: Out of scope for the mobile app: the app has no Rider role or Add Rider form (Logistics function, web).
A98: Rider - Account Creation | B98: Rider | C98: Required Fields | D98: TC-RID-003 | E98: Leave one required field blank at a time | F98: Each time, saving is blocked and a required-field message is shown on the blank field only. Other entered values (except uploads) are kept. No rider is created. | G98: The Add Rider form is not in the Flutter app. | H98: Blocked | I98: Out of scope for the mobile app: the app has no Rider role or Add Rider form (Logistics function, web).
A99: Rider - Account Creation | B99: Rider | C99: Name | D99: TC-RID-004 | E99: Name with numbers or symbols | F99: Saving is blocked. A message on each name field says only letters are allowed. | G99: The Add Rider form is not in the Flutter app. | H99: Blocked | I99: Out of scope for the mobile app: the app has no Rider role or Add Rider form (Logistics function, web).
A100: Rider - Account Creation | B100: Rider | C100: Name | D100: TC-RID-005 | E100: Name length at the limits | F100: 1 and 51 characters are rejected with a length message. 2 and 50 characters are accepted. | G100: The Add Rider form is not in the Flutter app. | H100: Blocked | I100: Out of scope for the mobile app: the app has no Rider role or Add Rider form (Logistics function, web).
A101: Rider - Account Creation | B101: Rider | C101: Date of Birth | D101: TC-RID-006 | E101: Age at the 18-year limit | F101: The 17-year-old date is rejected with a message that the person must be at least 18. The other two dates are accepted. | G101: The Add Rider form is not in the Flutter app. | H101: Blocked | I101: Out of scope for the mobile app: the app has no Rider role or Add Rider form (Logistics function, web).
A102: Rider - Account Creation | B102: Rider | C102: Email | D102: TC-RID-007 | E102: Email in an invalid format | F102: Each value is rejected with a message asking for a valid email address. No rider is created. | G102: The Add Rider form is not in the Flutter app. | H102: Blocked | I102: Out of scope for the mobile app: the app has no Rider role or Add Rider form (Logistics function, web).
A103: Rider - Account Creation | B103: Rider | C103: Email | D103: TC-RID-008 | E103: Email already used by an account of another role | F103: Saving is blocked. A message says the email is already in use. No rider is created. | G103: The Add Rider form is not in the Flutter app. | H103: Blocked | I103: Out of scope for the mobile app: the app has no Rider role or Add Rider form (Logistics function, web).
A104: Rider - Account Creation | B104: Rider | C104: Mobile Number | D104: TC-RID-009 | E104: Mobile number in an invalid format | F104: Each value is rejected with a message asking for a valid mobile number. | G104: The Add Rider form is not in the Flutter app. | H104: Blocked | I104: Out of scope for the mobile app: the app has no Rider role or Add Rider form (Logistics function, web).
A105: Rider - Account Creation | B105: Rider | C105: Mobile Number | D105: TC-RID-010 | E105: Mobile number length at the limits | F105: 10 and 12 digits are rejected with a length message. 11 digits is accepted. | G105: The Add Rider form is not in the Flutter app. | H105: Blocked | I105: Out of scope for the mobile app: the app has no Rider role or Add Rider form (Logistics function, web).
A106: Rider - Account Creation | B106: Rider | C106: Mobile Number | D106: TC-RID-011 | E106: Mobile number that is already registered | F106: Saving is blocked. A message says the mobile number is already in use. | G106: The Add Rider form is not in the Flutter app. | H106: Blocked | I106: Out of scope for the mobile app: the app has no Rider role or Add Rider form (Logistics function, web).
A107: Rider - Account Creation | B107: Rider | C107: License and Vehicle | D107: TC-RID-012 | E107: Driver's license number in an invalid format | F107: Each value is rejected with a message showing the format A00-00-000000. | G107: The Add Rider form is not in the Flutter app. | H107: Blocked | I107: Out of scope for the mobile app: the app has no Rider role or Add Rider form (Logistics function, web).
... A123: Rider - Account Creation | B123: Rider | C123: Access Control | D123: TC-RID-028 | E123: Rider is visible only to the company that created it | F123: Pedro Jose Garcia appears in the rider list of Bilis Hatid Express Inc. and does not appear in the rider list of Agila Cargo Movers Corp. | G123: Company ownership is a server rule. | H123: Blocked | I123: Needs live Laravel API (--dart-define=zefanya.useLiveApi=true).
A124: Rider - Account Creation | B124: Rider | C124: Access Control | D124: TC-RID-029 | E124: No public rider registration | F124: Rider is not offered as a self-registration role. The Add Rider deep link opens the login screen. | G124: Registration offers only Buyer and Courier. Rider is not a self-registration role. There are no deep links. | H124: Pass
A125: Rider - Account Creation | B125: Rider | C125: Access Control | D125: TC-RID-030 | E125: Buyer or seller opens the Add Rider form | F125: Add Rider is not shown. The deep link and the request are refused each time (401/403, access-denied screen or redirect). No rider can be created. | G125: Add Rider is not in the app; refusal is a server rule. | H125: Blocked | I125: Needs live Laravel API (--dart-define=zefanya.useLiveApi=true).
A126: Rider - Account Creation | B126: Rider | C126: Access Control | D126: TC-RID-031 | E126: Pending logistics account tries to add a rider | F126: The Add Rider option is not available. The deep link or request is denied or shows the under-review notice. No rider can be created. | G126: No Logistics role in the app. | H126: Blocked | I126: Needs live Laravel API (--dart-define=zefanya.useLiveApi=true).
A127: Rider - Account Creation | B127: Rider | C127: Access Control | D127: TC-RID-032 | E127: Open another role's screens | F127: No other role's menus are shown. Each deep link shows an access-denied message or returns to the rider home screen. The API request is refused (401/403). No data from the other role is shown. | G127: No deep links; the 401/403 part is server-side. | H127: Blocked | I127: Needs live Laravel API (--dart-define=zefanya.useLiveApi=true). Also needs a proxy tool (M11).
A128: Rider - Account Creation | B128: Rider | C128: Add Rider Form | D128: TC-RID-033 | E128: [Mobile] Each field opens the right keyboard | F128: Each field opens the keyboard listed in the test data. Password fields show no autocorrect or word suggestions. No field opens a keyboard that cannot type its valid value. | G128: Tests the Add Rider form, which is not in the app. | H128: Blocked | I128: Out of scope for the mobile app: the app has no Rider role or Add Rider form (Logistics function, web).
A129: Rider - Account Creation | B129: Rider | C129: Add Rider Form | D129: TC-RID-034 | E129: [Mobile] Keyboard never hides the active field or Save | F129: The focused field always scrolls into view above the keyboard, with its error message visible. Save can be reached and tapped. The keyboard closes when Done or the background is tapped. | G129: Tests the Add Rider form, which is not in the app. | H129: Blocked | I129: Out of scope for the mobile app: the app has no Rider role or Add Rider form (Logistics function, web).
A130: Rider - Account Creation | B130: Rider | C130: Add Rider Form | D130: TC-RID-035 | E130: [Mobile] App sent to the background while filling the form | F130: Each time, the app returns to the same form with every typed value still there (passwords may be cleared). The app does not restart, crash or jump to the login screen. No rider is created until Save is tapped. | G130: Tests the Add Rider form, which is not in the app. | H130: Blocked | I130: Out of scope for the mobile app: the app has no Rider role or Add Rider form (Logistics function, web).
A131: Rider - Account Creation | B131: Rider | C131: Add Rider Form | D131: TC-RID-036 | E131: [Mobile] Rotate the phone while the form has data | F131: Either the app stays in portrait, or the layout switches to landscape and back keeping every value and the error message. Nothing is cleared and the app does not crash. | G131: Tests the Add Rider form, which is not in the app. | H131: Blocked | I131: Out of scope for the mobile app: the app has no Rider role or Add Rider form (Logistics function, web).
A132: Rider - Account Creation | B132: Rider | C132: Add Rider Form | D132: TC-RID-037 | E132: [Mobile] Save with no internet connection | F132: Step 3: a clear no-internet message is shown, the typed data stays on the form, the app does not crash, and no rider is created. Step 4: the rider is saved once: exactly one rider and one activation email. | G132: Tests the Add Rider form, which is not in the app. | H132: Blocked | I132: Out of scope for the mobile app: the app has no Rider role or Add Rider form (Logistics function, web).
A133: Rider - Account Creation | B133: Rider | C133: Add Rider Form | D133: TC-RID-038 | E133: [Mobile] Connection drops right after tapping Save | F133: The app shows a connection error or a waiting state, never a frozen screen. In the end exactly one rider exists with this email. If the first attempt was saved, the app continues normally (or says the rider already exists and lets the user continue); the rider is never left in a state the user cannot reach. | G133: Tests the Add Rider form, which is not in the app. | H133: Blocked | I133: Out of scope for the mobile app: the app has no Rider role or Add Rider form (Logistics function, web).
A134: Rider - Account Creation | B134: Rider | C134: Add Rider Form | D134: TC-RID-039 | E134: [Mobile] System Back on the Add Rider form | F134: Leaving the form with typed data asks first, and Cancel keeps every value. After confirming, no rider is created and the rider list is unchanged. | G134: Tests the Add Rider form, which is not in the app. | H134: Blocked | I134: Out of scope for the mobile app: the app has no Rider role or Add Rider form (Logistics function, web).
A135: Rider - Account Creation | B135: Rider | C135: Document Upload | D135: TC-RID-040 | E135: [Mobile] Upload with the camera, the Files app and the gallery | F135: Each source (camera, Files, gallery) is offered and works. The camera photo shows a preview and is accepted (compressed to 5 MB or less if needed). The PDF and the gallery image show their names or previews. Save continues normally. | G135: Camera and Gallery only; no Files/PDF source in the picker. | H135: Blocked | I135: See TC-COU-045.
A136: Rider - Account Creation | B136: Rider | C136: Document Upload | D136: TC-RID-041 | E136: [Mobile] Camera or photo access denied | F136: No crash. A message explains why the permission is needed and offers a link to the phone's Settings. Files still works and the file is accepted. Asking again shows the system prompt again or the Settings message. | G136: No permission-denied message in the picker code. | H136: Blocked | I136: Needs a phone or emulator; code review only.
... A138: Rider - Account Creation | B138: Rider | C138: Add Rider Form | D138: TC-RID-043 | E138: [Mobile] Large system font on a small screen | F138: All labels, placeholders, error messages and buttons can be read in full; none are cut off or overlapping. The screen scrolls to every field and Save can be tapped. | G138: Tests the Add Rider form, which is not in the app. | H138: Blocked | I138: Out of scope for the mobile app: the app has no Rider role or Add Rider form (Logistics function, web).
A139: Rider - Account Creation | B139: Rider | C139: Account Activation | D139: TC-RID-044 | E139: [Mobile] Activation link opened on the rider's phone with the app installed | F139: The link opens the app's Set Password screen (or a mobile web page that leads back to the app). Activation succeeds, the status becomes Active, and the rider logs in to the rider home screen showing Mark Anthony Bautista. | G139: No deep-link or app-link handling in the app. | H139: Fail
A140: Rider - Account Creation | B140: Rider | C140: Account Activation | D140: TC-RID-045 | E140: [Mobile] Activation link opened on a phone without the app | F140: The link opens a mobile web page to set the password, or the app's store page with clear instructions. No blank or error page. | G140: No activation web page or store fallback in the app. | H140: Fail | I140: Needs the web side.
A141: Rider - Account Creation | B141: Rider | C141: Access Control | D141: TC-RID-046 | E141: [Mobile] Stay logged in after closing the app or restarting the phone | F141: Each time the app opens on the rider home screen still logged in, showing Pedro Jose Garcia. It does not ask to log in again and shows no other user's data. | G141: No Rider home screen. The courier session does persist (see TC-COU-051). | H141: Blocked | I141: Out of scope for the mobile app: the app has no Rider role or Add Rider form (Logistics function, web).
A142: Rider - Account Creation | B142: Rider | C142: Access Control | D142: TC-RID-047 | E142: [Mobile] Back after logging out | F142: The login screen stays. No screen with account data appears again, and the app does not log back in by itself. | G142: No Rider role. Logout works for the courier role (see TC-COU-052). | H142: Blocked | I142: Out of scope for the mobile app: the app has no Rider role or Add Rider form (Logistics function, web).
A143: Buyer - Modules | B143: B1 Account | C143: Account & Security | D143: BUY-ACCT-001 | E143: Edit profile with valid data | F143: A success message is shown. After a pull-to-refresh and re-login the new name and photo are shown on the profile screen and the account (Me) tab. Email and phone are unchanged. | G143: Edit Profile saves name, initial, sex, phone, address and photo to the phone only (no profile endpoint). | H143: Blocked | I143: Needs live Laravel API. Retest when the profile API exists.
A144: Buyer - Modules | B144: B1 Account | C144: Account & Security | D144: BUY-ACCT-002 | E144: Profile field validation | F144: Each is rejected with a field message; the saved profile is unchanged after a pull-to-refresh. | G144: Name fields only check length >= 2. No letters-only rule. | H144: Fail | I144: Same gap as TC-BUY-004.
A145: Buyer - Modules | B145: B1 Account | C145: Account & Security | D145: BUY-ACCT-003 | E145: Change password with the correct old password | F145: Password changes with a success message. The old password is rejected; the new one works. | G145: No change-password, change-email or change-phone screen. | H145: Fail | I145: Feature is not in the app.
A146: Buyer - Modules | B146: B1 Account | C146: Account & Security | D146: BUY-ACCT-004 | E146: Change password with a wrong old password | F146: Blocked with 'current password is incorrect'. The original password still works. | G146: No change-password, change-email or change-phone screen. | H146: Fail | I146: Feature is not in the app.
A147: Buyer - Modules | B147: B1 Account | C147: Account & Security | D147: BUY-ACCT-005 | E147: New password breaks the rule | F147: Each is rejected with the specific rule that failed. The password is unchanged. | G147: No change-password, change-email or change-phone screen. | H147: Fail | I147: Feature is not in the app.
A148: Buyer - Modules | B148: B1 Account | C148: Account & Security | D148: BUY-ACCT-006 | E148: Change email with verification | F148: Before verification the old email still logs in and the profile still shows it. After the correct OTP, only the new email logs in; the old one is rejected. | G148: No change-password, change-email or change-phone screen. | H148: Fail | I148: Feature is not in the app.
A149: Buyer - Modules | B149: B1 Account | C149: Account & Security | D149: BUY-ACCT-007 | E149: Change email: wrong or expired OTP | F149: Both are rejected. The email is not changed. | G149: No change-password, change-email or change-phone screen. | H149: Fail | I149: Feature is not in the app.
A150: Buyer - Modules | B150: B1 Account | C150: Account & Security | D150: BUY-ACCT-008 | E150: Change email to one already used | F150: Both are blocked with 'email already in use' and no OTP is sent. | G150: No change-password, change-email or change-phone screen. | H150: Fail | I150: Feature is not in the app.
A151: Buyer - Modules | B151: B1 Account | C151: Account & Security | D151: BUY-ACCT-009 | E151: Change phone with verification and format | F151: Invalid and duplicate numbers are rejected without an OTP. The valid number is saved only after verification. | G151: No change-password, change-email or change-phone screen. | H151: Fail | I151: Feature is not in the app.
...
